[{"id": 207543333550161921, "name": "Cam", "wins": 3, "losses": 6, "elo": 610}, {"id": 206623116992970752, "name": "Tommy", "wins": 6, "losses": 4, "elo": 858}, {"id": 810989086667571231, "name": "Dario", "wins": 6, "losses": 2, "elo": 909}, {"id": 324312288775634944, "name": "Kevin C.", "wins": 1, "losses": 3, "elo": 622}, {"id": 481936833442349066, "name": "Kyaw Pet Paw", "wins": 4, "losses": 4, "elo": 730}, {"id": 1005171177800613920, "name": "Jonathan S", "wins": 8, "losses": 2, "elo": 963}, {"id": 337980189021700096, "name": "Eddy", "wins": 6, "losses": 4, "elo": 803}, {"id": 286329770940039179, "name": "Neer", "wins": 5, "losses": 4, "elo": 791}, {"id": 743978080435175488, "name": "isabelle", "wins": 1, "losses": 8, "elo": 425}, {"id": 382029920320356352, "name": "rookie", "wins": 0, "losses": 0, "elo": 750}]