[{"id": 249493223505803058, "name": "Tommy", "wins": 4, "losses": 5, "elo": 1798}, {"id": 141605251791317960, "name": "Cam", "wins": 4, "losses": 2, "elo": 969}, {"id": 999384995746223147, "name": "Manny", "wins": 4, "losses": 3, "elo": 1125}, {"id": 631246236884898180, "name": "Massy", "wins": 1, "losses": 4, "elo": 936}, {"id": 233323458865648233, "name": "Isabelle", "wins": 3, "losses": 3, "elo": 1077}, {"id": 784077283235569329, "name": "Eddy", "wins": 3, "losses": 4, "elo": 1459}, {"id": 616700490878458221, "name": "Sohan", "wins": 4, "losses": 4, "elo": 687}, {"id": 259416812576521706, "name": "JR", "wins": 6, "losses": 2, "elo": 1204}, {"id": 551307948139589012, "name": "Kyaw", "wins": 7, "losses": 3, "elo": 1298}]